pybashproof.py
pybashproof-0.1.2.dist-info/LICENSE
pybashproof-0.1.2.dist-info/METADATA
pybashproof-0.1.2.dist-info/WHEEL
pybashproof-0.1.2.dist-info/entry_points.txt
pybashproof-0.1.2.dist-info/top_level.txt
pybashproof-0.1.2.dist-info/RECORD
