Metadata-Version: 2.1
Name: pybashproof
Version: 0.1.2
Summary: Conceptual bash-shell tracking and logging.
Author-email: bitdruid <bitdruid@outlook.com>
License: MIT License
Project-URL: Homepage, https://github.com/bitdruid/forensic_concepts
Keywords: bash,shell,tracking,logging
Classifier: Programming Language :: Python :: 3.6
Classifier: License :: OSI Approved :: MIT License
Classifier: Operating System :: OS Independent
Requires-Python: >=3.6
License-File: LICENSE
